.gitignore
LICENSE.txt
README.md
setup.cfg
setup.py
ppdl/__init__.py
ppdl/howto-publish.txt
ppdl/models.py
ppdl/sym.py
ppdl.egg-info/PKG-INFO
ppdl.egg-info/SOURCES.txt
ppdl.egg-info/dependency_links.txt
ppdl.egg-info/not-zip-safe
ppdl.egg-info/requires.txt
ppdl.egg-info/top_level.txt
ppdl/bin/get_scm_version
video-production/README.md
video-production/bin/Dockerfile
video-production/bin/build-docker-image
video-production/bin/run
video-production/refs/manimgl/Bubbles_speech.svg
video-production/refs/manimgl/Bubbles_thought.svg
video-production/refs/manimgl/Untitled.ipynb
video-production/refs/manimgl/chess.py
video-production/refs/manimgl/custom_config.yml
video-production/refs/manimgl/drawings.py
video-production/refs/manimgl/example_scenes.py
video-production/refs/manimgl/links.txt
video-production/refs/manimgl/list_videos.txt
video-production/refs/manimgl/manim_imports_ext.py
video-production/refs/manimgl/objects.py
video-production/refs/manimgl/scene.py
video-production/refs/manimgl/custom/backdrops.py
video-production/refs/manimgl/custom/banner.py
video-production/refs/manimgl/custom/deprecated.py
video-production/refs/manimgl/custom/drawings.py
video-production/refs/manimgl/custom/end_screen.py
video-production/refs/manimgl/custom/filler.py
video-production/refs/manimgl/custom/logo.py
video-production/refs/manimgl/custom/opening_quote.py
video-production/refs/manimgl/custom/characters/pi_class.py
video-production/refs/manimgl/custom/characters/pi_creature.py
video-production/refs/manimgl/custom/characters/pi_creature_animations.py
video-production/refs/manimgl/custom/characters/pi_creature_scene.py
video-production/refs/manimgl/docker/Dockerfile
video-production/refs/manimgl/docker/run.sh
video-production/refs/manimgl/pi_creature_images/angry.svg
video-production/refs/manimgl/pi_creature_images/baselink.txt
video-production/refs/manimgl/pi_creature_images/confused.svg
video-production/refs/manimgl/pi_creature_images/erm.svg
video-production/refs/manimgl/pi_creature_images/happy.svg
video-production/refs/manimgl/pi_creature_images/hesitant.svg
video-production/refs/manimgl/pi_creature_images/hooray.svg
