Metadata-Version: 2.1
Name: ppdl
Version: 0.1.3
Summary: Utils on the course Probabilistic Programming for Deep Learning
Home-page: https://github.com/rramosp/ppdl/
Author: raul ramos
Author-email: raul.ramos@udea.edu.co
License: UNKNOWN
Platform: UNKNOWN
License-File: LICENSE.txt
